verifyvoice
